LICENSE
MANIFEST.in
README.md
gorella.py
setup.py
tests.py
tests_uni.py
gorella.egg-info/PKG-INFO
gorella.egg-info/SOURCES.txt
gorella.egg-info/dependency_links.txt
gorella.egg-info/top_level.txt